README.md
README.rst
setup.py
sympound/__init__.py
sympound/sympound.py
sympound.egg-info/PKG-INFO
sympound.egg-info/SOURCES.txt
sympound.egg-info/dependency_links.txt
sympound.egg-info/top_level.txt