Metadata-Version: 2.1
Name: sympound
Version: 0.6.0
Summary: Python implementation of SymSpell Compound
Home-page: https://github.com/Esukhia/sympound-python
Author: Esukhia development team
Author-email: esukhiadev@gmail.com
License: MIT
Project-URL: Source, https://github.com/Esukhia/sympound-python
Project-URL: Tracker, https://github.com/Esukhia/sympound-python/issues
Keywords: spell check
Platform: UNKNOWN
Classifier: Development Status :: 3 - Alpha
Classifier: Topic :: Text Processing :: Linguistic
Classifier: Programming Language :: Python :: 3
Classifier: Operating System :: OS Independent
Classifier: Intended Audience :: Developers
Classifier: Intended Audience :: Science/Research
Classifier: License :: OSI Approved :: MIT License
Requires-Python: >=3
